sigma/backends/golangexpr/__init__.py
sigma/backends/golangexpr/golangexpr.py
pysigma_backend_golangexpr-1.0.0.dist-info/METADATA
pysigma_backend_golangexpr-1.0.0.dist-info/WHEEL
pysigma_backend_golangexpr-1.0.0.dist-info/licenses/LICENSE
pysigma_backend_golangexpr-1.0.0.dist-info/RECORD
