Metadata-Version: 2.4
Name: pySigma-backend-golangexpr
Version: 1.0.0
Summary: pySigma Golang Expr backend
License: MIT
License-File: LICENSE
Author: Paul Hager
Requires-Python: >=3.10,<4.0
Classifier: License :: OSI Approved :: MIT License
Classifier: Programming Language :: Python :: 3
Classifier: Programming Language :: Python :: 3.10
Classifier: Programming Language :: Python :: 3.11
Classifier: Programming Language :: Python :: 3.12
Classifier: Programming Language :: Python :: 3.13
Classifier: Programming Language :: Python :: 3.14
Requires-Dist: pysigma (>=1.0,<2.0)
Requires-Dist: pysigma-backend-elasticsearch (>=2.0,<3.0)
Project-URL: Repository, https://github.com/pH-T/pySigma-backend-golangexpr
